sparkpdf/VERSION
sparkpdf/__init__.py
sparkpdf/enums.py
sparkpdf/image/DataToImage.py
sparkpdf/image/ImageDrawBoxes.py
sparkpdf/image/__init__.py
sparkpdf/models/__init__.py
sparkpdf/models/ner/BaseNer.py
sparkpdf/models/ner/Ner.py
sparkpdf/models/ner/__init__.py
sparkpdf/models/recognizers/TesseractOcr.py
sparkpdf/models/recognizers/__init__.py
sparkpdf/params.py
sparkpdf/pdf/PdfDataToImage.py
sparkpdf/pdf/__init__.py
sparkpdf/pipeline/PandasPipeline.py
sparkpdf/pipeline/__init__.py
sparkpdf/resources/images/SparkPdfLogo.png
sparkpdf/resources/pdfs/SparkPdf.pdf
sparkpdf/resources/pdfs/example.pdf
sparkpdf/schemas/Box.py
sparkpdf/schemas/Document.py
sparkpdf/schemas/Entity.py
sparkpdf/schemas/Image.py
sparkpdf/schemas/NerOutput.py
sparkpdf/schemas/__init__.py
sparkpdf/text/TextToDocument.py
sparkpdf/text/__init__.py
sparkpdf/utils/__init__.py
sparkpdf/utils/auxiliary.py
sparkpdf/utils/dataclass.py
sparkpdf/utils/show_utils.py
sparkpdf/utils/templates/base.html
sparkpdf/utils/templates/image.html
sparkpdf/utils/templates/ner.html
sparkpdf/utils/templates/text.html
pyspark_pdf-0.1.0rc9.dist-info/LICENSE
pyspark_pdf-0.1.0rc9.dist-info/METADATA
pyspark_pdf-0.1.0rc9.dist-info/WHEEL
pyspark_pdf-0.1.0rc9.dist-info/RECORD
