Metadata-Version: 2.1
Name: pyspark-pdf
Version: 0.1.0rc9
Summary: Spark-Pdf is a library for processing documents using Apache Spark
Home-page: https://github.com/StabRise/spark-pdf
License: AGPL-3.0
Author: Mykola Melnyk
Author-email: mykola@stabrise.com
Requires-Python: >=3.10,<4.0
Classifier: License :: OSI Approved :: GNU Affero General Public License v3
Classifier: Programming Language :: Python :: 3
Classifier: Programming Language :: Python :: 3.10
Classifier: Programming Language :: Python :: 3.11
Classifier: Programming Language :: Python :: 3.12
Classifier: Programming Language :: Python :: 3.13
Provides-Extra: ml
Requires-Dist: PyMuPDF (==1.24.11)
Requires-Dist: imagesize (==1.4.1)
Requires-Dist: numpy (>=1.26.4,<2.0.0)
Requires-Dist: pandas (>=2.2.2,<3.0.0)
Requires-Dist: pillow (>=10.4.0,<11.0.0)
Requires-Dist: pyarrow (==17.0.0)
Requires-Dist: pyspark (==3.5.3)
Requires-Dist: pytesseract (==0.3.13)
Requires-Dist: pytest (>=7.4.4,<8.0.0)
Requires-Dist: torch (>=2.3.0,<3.0.0) ; extra == "ml"
Requires-Dist: transformers (>=4.42.0,<5.0.0) ; extra == "ml"
Project-URL: Repository, https://github.com/StabRise/spark-pdf
